LICENSE.txt
MANIFEST.in
README.rst
release_history.rst
requirements.txt
setup.py
filetool/__init__.py
filetool/backup.py
filetool/files.py
filetool/meth.py
filetool/printer.py
filetool/py23.py
filetool/winzip.py
filetool/zzz_manual_install.py
filetool.egg-info/PKG-INFO
filetool.egg-info/SOURCES.txt
filetool.egg-info/dependency_links.txt
filetool.egg-info/top_level.txt
filetool/__pycache__/__init__.cpython-33.pyc