Metadata-Version: 1.1
Name: filetool
Version: 0.0.4
Summary: File manipulate tools.
Home-page: https://github.com/MacHu-GWU/filetool-project
Author: Sanhe Hu
Author-email: husanhe@gmail.com
License: UNKNOWN
Download-URL: https://github.com/MacHu-GWU/filetool-project/tarball/2016-09-14
Platform: Windows
Platform: MacOS
Platform: Unix
Classifier: Development Status :: 4 - Beta
Classifier: Intended Audience :: Developers
Classifier: License :: OSI Approved :: MIT License
Classifier: Natural Language :: English
Classifier: Operating System :: Microsoft :: Windows
Classifier: Operating System :: MacOS
Classifier: Operating System :: Unix
Classifier: Programming Language :: Python
Classifier: Programming Language :: Python :: 2.7
Classifier: Programming Language :: Python :: 3.3
Classifier: Programming Language :: Python :: 3.4
Classifier: Programming Language :: Python :: 3.5
